mlc/__init__.py
mlc/__main__.py
mlc/action.py
mlc/action_factory.py
mlc/cache_action.py
mlc/cfg_action.py
mlc/error_codes.py
mlc/experiment_action.py
mlc/index.py
mlc/item.py
mlc/logger.py
mlc/main.py
mlc/repo.py
mlc/repo_action.py
mlc/script_action.py
mlc/utils.py
mlcflow-1.1.19.dist-info/licenses/LICENSE.md
mlcflow-1.1.19.dist-info/METADATA
mlcflow-1.1.19.dist-info/WHEEL
mlcflow-1.1.19.dist-info/entry_points.txt
mlcflow-1.1.19.dist-info/top_level.txt
mlcflow-1.1.19.dist-info/RECORD
