Metadata-Version: 2.4
Name: mlcflow
Version: 1.1.19
Summary: An automation interface tailored for CPU/GPU benchmarking
Author-email: MLCommons <systems@mlcommons.org>
License: 
Project-URL: Homepage, https://github.com/mlcommons/mlcflow
Project-URL: Documentation, https://docs.mlcommons.org/mlcflow
Project-URL: Repository, https://github.com/mlcommons/mlcflow
Project-URL: Issues, https://github.com/mlcommons/mlcflow/issues
Keywords: mlc,mlcflow,pypi,package,automation
Classifier: Programming Language :: Python :: 3
Classifier: License :: OSI Approved :: Apache Software License
Classifier: Operating System :: OS Independent
Requires-Python: >=3.7
License-File: LICENSE.md
Requires-Dist: requests
Requires-Dist: pyyaml
Requires-Dist: giturlparse
Requires-Dist: colorama
Dynamic: license-file
